departments/__init__.py
departments/admin.py
departments/apps.py
departments/static/css/departments/medilab_ds.css
departments/templates/departments/_common.html
departments/templates/departments/medilab_ds.html
departments/templatetags/__init__.py
departments/templatetags/departments_tags.py
django_medilab_components-0.0.9.dist-info/LICENSE
django_medilab_components-0.0.9.dist-info/METADATA
django_medilab_components-0.0.9.dist-info/WHEEL
django_medilab_components-0.0.9.dist-info/top_level.txt
django_medilab_components-0.0.9.dist-info/RECORD
